[
  {"velocity": 0, "color": [0, 0, 0]},
  {"velocity": 1, "color": [114, 114, 114]},
  {"velocity": 2, "color": [152, 152, 152]},
  {"velocity": 3, "color": [175, 175, 175]},
  {"velocity": 4, "color": [175, 55, 55]},
  {"velocity": 5, "color": [175, 0, 0]},
  {"velocity": 6, "color": [147, 0, 0]},
  {"velocity": 7, "color": [117, 0, 0]},
  {"velocity": 8, "color": [175, 107, 41]},
  {"velocity": 9, "color": [175, 42, 0]},
  {"velocity": 10, "color": [149, 42, 0]},
  {"velocity": 11, "color": [145, 27, 0]},
  {"velocity": 12, "color": [175, 128, 41]},
  {"velocity": 13, "color": [175, 171, 0]},
  {"velocity": 14, "color": [149, 128, 0]},
  {"velocity": 15, "color": [124, 124, 0]},
  {"velocity": 16, "color": [73, 175, 50]},
  {"velocity": 17, "color": [50, 175, 0]},
  {"velocity": 18, "color": [39, 149, 0]},
  {"velocity": 19, "color": [38, 105, 0]},
  {"velocity": 20, "color": [42, 175, 77]},
  {"velocity": 21, "color": [42, 171, 0]},
  {"velocity": 22, "color": [42, 149, 0]},
  {"velocity": 23, "color": [42, 110, 0]},
  {"velocity": 24, "color": [73, 175, 80]},
  {"velocity": 25, "color": [42, 175, 30]},
  {"velocity": 26, "color": [42, 149, 18]},
  {"velocity": 27, "color": [42, 124, 11]},
  {"velocity": 28, "color": [73, 175, 94]},
  {"velocity": 29, "color": [42, 175, 94]},
  {"velocity": 30, "color": [42, 149, 77]},
  {"velocity": 31, "color": [42, 124, 81]},
  {"velocity": 32, "color": [73, 175, 128]},
  {"velocity": 33, "color": [42, 175, 128]},
  {"velocity": 34, "color": [42, 149, 104]},
  {"velocity": 35, "color": [42, 124, 104]},
  {"velocity": 36, "color": [73, 175, 175]},
  {"velocity": 37, "color": [42, 171, 175]},
  {"velocity": 38, "color": [42, 149, 149]},
  {"velocity": 39, "color": [42, 128, 110]},
  {"velocity": 40, "color": [118, 152, 175]},
  {"velocity": 41, "color": [42, 124, 175]},
  {"velocity": 42, "color": [42, 105, 149]},
  {"velocity": 43, "color": [42, 85, 110]},
  {"velocity": 44, "color": [118, 124, 175]},
  {"velocity": 45, "color": [42, 42, 171]},
  {"velocity": 46, "color": [42, 42, 149]},
  {"velocity": 47, "color": [42, 42, 110]},
  {"velocity": 48, "color": [128, 116, 175]},
  {"velocity": 49, "color": [73, 42, 175]},
  {"velocity": 50, "color": [68, 42, 149]},
  {"velocity": 51, "color": [62, 42, 124]},
  {"velocity": 52, "color": [175, 94, 128]},
  {"velocity": 53, "color": [175, 42, 128]},
  {"velocity": 54, "color": [149, 42, 112]},
  {"velocity": 55, "color": [124, 42, 67]},
  {"velocity": 56, "color": [175, 73, 101]},
  {"velocity": 57, "color": [175, 42, 96]},
  {"velocity": 58, "color": [149, 42, 39]},
  {"velocity": 59, "color": [128, 42, 22]},
  {"velocity": 60, "color": [175, 42, 27]},
  {"velocity": 61, "color": [175, 77, 27]},
  {"velocity": 62, "color": [149, 128, 27]},
  {"velocity": 63, "color": [118, 128, 27]},
  {"velocity": 64, "color": [62, 128, 27]},
  {"velocity": 65, "color": [55, 107, 35]},
  {"velocity": 66, "color": [42, 73, 128]},
  {"velocity": 67, "color": [42, 42, 175]},
  {"velocity": 68, "color": [42, 104, 83]},
  {"velocity": 69, "color": [62, 42, 175]},
  {"velocity": 70, "color": [149, 140, 124]},
  {"velocity": 71, "color": [84, 84, 84]},
  {"velocity": 72, "color": [175, 42, 42]},
  {"velocity": 73, "color": [124, 175, 42]},
  {"velocity": 74, "color": [118, 149, 42]},
  {"velocity": 75, "color": [62, 149, 42]},
  {"velocity": 76, "color": [42, 149, 27]},
  {"velocity": 77, "color": [42, 147, 77]},
  {"velocity": 78, "color": [42, 147, 149]},
  {"velocity": 79, "color": [42, 77, 149]},
  {"velocity": 80, "color": [62, 42, 149]},
  {"velocity": 81, "color": [104, 42, 149]},
  {"velocity": 82, "color": [175, 73, 124]},
  {"velocity": 83, "color": [104, 42, 27]},
  {"velocity": 84, "color": [175, 62, 42]},
  {"velocity": 85, "color": [124, 175, 42]},
  {"velocity": 86, "color": [118, 175, 42]},
  {"velocity": 87, "color": [62, 175, 42]},
  {"velocity": 88, "color": [84, 175, 55]},
  {"velocity": 89, "color": [84, 175, 104]},
  {"velocity": 90, "color": [84, 175, 149]},
  {"velocity": 91, "color": [118, 149, 175]},
  {"velocity": 92, "color": [84, 107, 128]},
  {"velocity": 93, "color": [118, 104, 149]},
  {"velocity": 94, "color": [149, 73, 175]},
  {"velocity": 95, "color": [175, 42, 96]},
  {"velocity": 96, "color": [175, 62, 42]},
  {"velocity": 97, "color": [147, 140, 42]},
  {"velocity": 98, "color": [118, 175, 42]},
  {"velocity": 99, "color": [124, 105, 42]},
  {"velocity": 100, "color": [118, 91, 42]},
  {"velocity": 101, "color": [62, 118, 55]},
  {"velocity": 102, "color": [62, 118, 84]},
  {"velocity": 103, "color": [84, 73, 84]},
  {"velocity": 104, "color": [62, 91, 104]},
  {"velocity": 105, "color": [118, 104, 62]},
  {"velocity": 106, "color": [118, 62, 62]},
  {"velocity": 107, "color": [147, 73, 62]},
  {"velocity": 108, "color": [149, 105, 62]},
  {"velocity": 109, "color": [157, 118, 62]},
  {"velocity": 110, "color": [130, 157, 73]},
  {"velocity": 111, "color": [105, 147, 62]},
  {"velocity": 112, "color": [62, 62, 84]},
  {"velocity": 113, "color": [157, 157, 118]},
  {"velocity": 114, "color": [115, 157, 118]},
  {"velocity": 115, "color": [115, 134, 157]},
  {"velocity": 116, "color": [130, 128, 157]},
  {"velocity": 117, "color": [91, 91, 91]},
  {"velocity": 118, "color": [132, 132, 132]},
  {"velocity": 119, "color": [143, 146, 143]},
  {"velocity": 120, "color": [140, 56, 56]},
  {"velocity": 121, "color": [107, 56, 56]},
  {"velocity": 122, "color": [56, 140, 56]},
  {"velocity": 123, "color": [56, 122, 56]},
  {"velocity": 124, "color": [140, 140, 56]},
  {"velocity": 125, "color": [122, 94, 56]},
  {"velocity": 126, "color": [132, 94, 56]},
  {"velocity": 127, "color": [104, 56, 56]}
]
